tethys_dask_scheduler/__init__.py
tethys_dask_scheduler/plugin.py
tethys_dask_scheduler-2.0.0.dist-info/LICENSE
tethys_dask_scheduler-2.0.0.dist-info/METADATA
tethys_dask_scheduler-2.0.0.dist-info/WHEEL
tethys_dask_scheduler-2.0.0.dist-info/top_level.txt
tethys_dask_scheduler-2.0.0.dist-info/RECORD
