Metadata-Version: 2.1
Name: tethys-dask-scheduler
Version: 2.0.0
Summary: A Dask scheduler with custom SchedulerPlugins to support integration with Tethys Platform
Home-page: https://github.com/tethysplatform/tethys_dask_scheduler
Author: Nathan Swain
Author-email: nswain@aquaveo.com
License: UNKNOWN
Project-URL: Documentation, http://docs.tethysplatform.org/en/stable/tutorials/dask/setup_scheduler.html
Platform: UNKNOWN
Classifier: Development Status :: 5 - Production/Stable
Classifier: Environment :: Web Environment
Classifier: Intended Audience :: Developers
Classifier: License :: OSI Approved :: BSD License
Classifier: Natural Language :: English
Classifier: Operating System :: OS Independent
Classifier: Programming Language :: Python :: 3
Classifier: Programming Language :: Python :: 3.6
Classifier: Programming Language :: Python :: 3.7
Classifier: Programming Language :: Python :: 3.8
Classifier: Programming Language :: Python :: 3.9
Classifier: Programming Language :: Python :: 3.10
Classifier: Programming Language :: Python :: Implementation
Classifier: Topic :: Scientific/Engineering
Classifier: Topic :: Scientific/Engineering :: GIS
Classifier: Topic :: Scientific/Engineering :: Information Analysis
Classifier: Topic :: Software Development :: Libraries
Classifier: Topic :: Utilities
Requires-Python: >=3.6
License-File: LICENSE
Requires-Dist: click
Requires-Dist: distributed
Provides-Extra: tests
Requires-Dist: tox ; extra == 'tests'
